tinycircuits_attiny25/__init__.py
tinycircuits_attiny25/tinycircuits_attiny25.py
tinycircuits_attiny25-0.0.1.dist-info/LICENSE
tinycircuits_attiny25-0.0.1.dist-info/METADATA
tinycircuits_attiny25-0.0.1.dist-info/WHEEL
tinycircuits_attiny25-0.0.1.dist-info/top_level.txt
tinycircuits_attiny25-0.0.1.dist-info/RECORD
